{
    "success": 1,
    "result": [
        {
            "player_key": 1441,
            "player_name": "C. Dinu",
            "player_country": "Romania",
            "player_bday": "18.01.1993",
            "player_logo": "https://api.api-tennis.com/logo-tennis/1441_c-dinu.jpg",
            "stats": [
                {
                    "season": "2022",
                    "type": "doubles",
                    "rank": "250",
                    "titles": "1",
                    "matches_won": "22",
                    "matches_lost": "20",
                    "hard_won": "6",
                    "hard_lost": "5",
                    "clay_won": "16",
                    "clay_lost": "15",
                    "grass_won": "",
                    "grass_lost": ""
                },
                {
                    "season": "2021",
                    "type": "doubles",
                    "rank": "346",
                    "titles": "3",
                    "matches_won": "23",
                    "matches_lost": "7",
                    "hard_won": "2",
                    "hard_lost": "2",
                    "clay_won": "21",
                    "clay_lost": "5",
                    "grass_won": "",
                    "grass_lost": ""
                },
                {
                    "season": "2020",
                    "type": "doubles",
                    "rank": "241",
                    "titles": "1",
                    "matches_won": "9",
                    "matches_lost": "5",
                    "hard_won": "",
                    "hard_lost": "",
                    "clay_won": "9",
                    "clay_lost": "5",
                    "grass_won": "",
                    "grass_lost": ""
                },
                {
                    "season": "2019",
                    "type": "doubles",
                    "rank": "223",
                    "titles": "0",
                    "matches_won": "0",
                    "matches_lost": "2",
                    "hard_won": "",
                    "hard_lost": "",
                    "clay_won": "0",
                    "clay_lost": "2",
                    "grass_won": "",
                    "grass_lost": ""
                },
                {
                    "season": "2017",
                    "type": "doubles",
                    "rank": "255",
                    "titles": "0",
                    "matches_won": "1",
                    "matches_lost": "1",
                    "hard_won": "",
                    "hard_lost": "",
                    "clay_won": "1",
                    "clay_lost": "1",
                    "grass_won": "",
                    "grass_lost": ""
                },
                {
                    "season": "2016",
                    "type": "doubles",
                    "rank": "213",
                    "titles": "0",
                    "matches_won": "1",
                    "matches_lost": "2",
                    "hard_won": "",
                    "hard_lost": "",
                    "clay_won": "1",
                    "clay_lost": "2",
                    "grass_won": "",
                    "grass_lost": ""
                },
                {
                    "season": "2015",
                    "type": "doubles",
                    "rank": "234",
                    "titles": "0",
                    "matches_won": "0",
                    "matches_lost": "1",
                    "hard_won": "",
                    "hard_lost": "",
                    "clay_won": "0",
                    "clay_lost": "1",
                    "grass_won": "",
                    "grass_lost": ""
                },
                {
                    "season": "2012",
                    "type": "doubles",
                    "rank": "275",
                    "titles": "0",
                    "matches_won": "2",
                    "matches_lost": "1",
                    "hard_won": "",
                    "hard_lost": "",
                    "clay_won": "2",
                    "clay_lost": "1",
                    "grass_won": "",
                    "grass_lost": ""
                },
                {
                    "season": "2011",
                    "type": "doubles",
                    "rank": "330",
                    "titles": "1",
                    "matches_won": "10",
                    "matches_lost": "6",
                    "hard_won": "",
                    "hard_lost": "",
                    "clay_won": "10",
                    "clay_lost": "6",
                    "grass_won": "",
                    "grass_lost": ""
                },
                {
                    "season": "2022",
                    "type": "singles",
                    "rank": "313",
                    "titles": "0",
                    "matches_won": "31",
                    "matches_lost": "27",
                    "hard_won": "6",
                    "hard_lost": "9",
                    "clay_won": "25",
                    "clay_lost": "17",
                    "grass_won": "0",
                    "grass_lost": "1"
                },
                {
                    "season": "2021",
                    "type": "singles",
                    "rank": "256",
                    "titles": "6",
                    "matches_won": "42",
                    "matches_lost": "10",
                    "hard_won": "1",
                    "hard_lost": "2",
                    "clay_won": "41",
                    "clay_lost": "8",
                    "grass_won": "",
                    "grass_lost": ""
                },
                {
                    "season": "2020",
                    "type": "singles",
                    "rank": "632",
                    "titles": "0",
                    "matches_won": "9",
                    "matches_lost": "6",
                    "hard_won": "",
                    "hard_lost": "",
                    "clay_won": "9",
                    "clay_lost": "6",
                    "grass_won": "",
                    "grass_lost": ""
                },
                {
                    "season": "2019",
                    "type": "singles",
                    "rank": "645",
                    "titles": "0",
                    "matches_won": "1",
                    "matches_lost": "2",
                    "hard_won": "",
                    "hard_lost": "",
                    "clay_won": "1",
                    "clay_lost": "2",
                    "grass_won": "",
                    "grass_lost": ""
                },
                {
                    "season": "2018",
                    "type": "singles",
                    "rank": "456",
                    "titles": "0",
                    "matches_won": "0",
                    "matches_lost": "2",
                    "hard_won": "",
                    "hard_lost": "",
                    "clay_won": "0",
                    "clay_lost": "2",
                    "grass_won": "",
                    "grass_lost": ""
                },
                {
                    "season": "2017",
                    "type": "singles",
                    "rank": "318",
                    "titles": "0",
                    "matches_won": "0",
                    "matches_lost": "3",
                    "hard_won": "",
                    "hard_lost": "",
                    "clay_won": "0",
                    "clay_lost": "3",
                    "grass_won": "",
                    "grass_lost": ""
                },
                {
                    "season": "2016",
                    "type": "singles",
                    "rank": "269",
                    "titles": "0",
                    "matches_won": "12",
                    "matches_lost": "14",
                    "hard_won": "3",
                    "hard_lost": "4",
                    "clay_won": "9",
                    "clay_lost": "10",
                    "grass_won": "",
                    "grass_lost": ""
                },
                {
                    "season": "2015",
                    "type": "singles",
                    "rank": "229",
                    "titles": "0",
                    "matches_won": "7",
                    "matches_lost": "6",
                    "hard_won": "3",
                    "hard_lost": "3",
                    "clay_won": "4",
                    "clay_lost": "3",
                    "grass_won": "",
                    "grass_lost": ""
                },
                {
                    "season": "2014",
                    "type": "singles",
                    "rank": "407",
                    "titles": "0",
                    "matches_won": "2",
                    "matches_lost": "2",
                    "hard_won": "",
                    "hard_lost": "",
                    "clay_won": "2",
                    "clay_lost": "2",
                    "grass_won": "",
                    "grass_lost": ""
                },
                {
                    "season": "2013",
                    "type": "singles",
                    "rank": "222",
                    "titles": "1",
                    "matches_won": "9",
                    "matches_lost": "11",
                    "hard_won": "0",
                    "hard_lost": "5",
                    "clay_won": "9",
                    "clay_lost": "6",
                    "grass_won": "",
                    "grass_lost": ""
                },
                {
                    "season": "2012",
                    "type": "singles",
                    "rank": "238",
                    "titles": "0",
                    "matches_won": "7",
                    "matches_lost": "9",
                    "hard_won": "0",
                    "hard_lost": "3",
                    "clay_won": "7",
                    "clay_lost": "6",
                    "grass_won": "",
                    "grass_lost": ""
                },
                {
                    "season": "2011",
                    "type": "singles",
                    "rank": "306",
                    "titles": "1",
                    "matches_won": "17",
                    "matches_lost": "7",
                    "hard_won": "0",
                    "hard_lost": "1",
                    "clay_won": "17",
                    "clay_lost": "6",
                    "grass_won": "",
                    "grass_lost": ""
                },
                {
                    "season": "2023",
                    "type": "doubles",
                    "rank": "265",
                    "titles": "3",
                    "matches_won": "23",
                    "matches_lost": "17",
                    "hard_won": "2",
                    "hard_lost": "2",
                    "clay_won": "21",
                    "clay_lost": "15",
                    "grass_won": "",
                    "grass_lost": ""
                },
                {
                    "season": "2023",
                    "type": "singles",
                    "rank": "281",
                    "titles": "0",
                    "matches_won": "41",
                    "matches_lost": "25",
                    "hard_won": "0",
                    "hard_lost": "1",
                    "clay_won": "41",
                    "clay_lost": "24",
                    "grass_won": "",
                    "grass_lost": ""
                },
                {
                    "season": "2024",
                    "type": "doubles",
                    "rank": "280",
                    "titles": "1",
                    "matches_won": "13",
                    "matches_lost": "8",
                    "hard_won": "",
                    "hard_lost": "",
                    "clay_won": "13",
                    "clay_lost": "8",
                    "grass_won": "",
                    "grass_lost": ""
                },
                {
                    "season": "2024",
                    "type": "singles",
                    "rank": "240",
                    "titles": "2",
                    "matches_won": "22",
                    "matches_lost": "13",
                    "hard_won": "",
                    "hard_lost": "",
                    "clay_won": "22",
                    "clay_lost": "13",
                    "grass_won": "",
                    "grass_lost": ""
                }
            ],
            "tournaments": [
                {
                    "name": "W25 Pescara (ITF)",
                    "season": "2021",
                    "type": "doubles",
                    "surface": "clay",
                    "prize": "$25,000"
                },
                {
                    "name": "W15 Antalya 19 (ITF)",
                    "season": "2021",
                    "type": "doubles",
                    "surface": "clay",
                    "prize": "$15,000"
                },
                {
                    "name": "W15 Antalya 7 (ITF)",
                    "season": "2021",
                    "type": "doubles",
                    "surface": "clay",
                    "prize": "$15,000"
                },
                {
                    "name": "W15 Varna (ITF)",
                    "season": "2020",
                    "type": "doubles",
                    "surface": "clay",
                    "prize": "$15000"
                },
                {
                    "name": "Bucharest (ITF)",
                    "season": "2011",
                    "type": "doubles",
                    "surface": "clay",
                    "prize": "$10,000"
                },
                {
                    "name": "W25 Vienna (ITF)",
                    "season": "2021",
                    "type": "singles",
                    "surface": "clay",
                    "prize": "$25,000"
                },
                {
                    "name": "W25 Vrnjacka Banja (ITF)",
                    "season": "2021",
                    "type": "singles",
                    "surface": "clay",
                    "prize": "$25,000"
                },
                {
                    "name": "W25 Tarvisio (ITF)",
                    "season": "2021",
                    "type": "singles",
                    "surface": "clay",
                    "prize": "$25,000"
                },
                {
                    "name": "W15 Antalya 20 (ITF)",
                    "season": "2021",
                    "type": "singles",
                    "surface": "clay",
                    "prize": "$15,000"
                },
                {
                    "name": "W15 Antalya 19 (ITF)",
                    "season": "2021",
                    "type": "singles",
                    "surface": "clay",
                    "prize": "$15,000"
                },
                {
                    "name": "W15 Antalya 12 (ITF)",
                    "season": "2021",
                    "type": "singles",
                    "surface": "clay",
                    "prize": "$15,000"
                },
                {
                    "name": "W15 Antalya (ITF)",
                    "season": "2013",
                    "type": "singles",
                    "surface": "clay",
                    "prize": "$10,000"
                },
                {
                    "name": "Bucharest (ITF)",
                    "season": "2011",
                    "type": "singles",
                    "surface": "clay",
                    "prize": "$10,000"
                },
                {
                    "name": "W25 Vrnjacka Banja (ITF)",
                    "season": "2022",
                    "type": "doubles",
                    "surface": "clay",
                    "prize": "$25,000"
                },
                {
                    "name": "W25 Antalya (ITF)",
                    "season": "2023",
                    "type": "doubles",
                    "surface": "clay",
                    "prize": "$25,000"
                },
                {
                    "name": "W25 Prokuplje (ITF)",
                    "season": "2023",
                    "type": "doubles",
                    "surface": "clay",
                    "prize": "$25,000"
                },
                {
                    "name": "W40 Pazardzhik (ITF)",
                    "season": "2023",
                    "type": "doubles",
                    "surface": "clay",
                    "prize": "$40,000"
                },
                {
                    "name": "W35 Antalya (ITF)",
                    "season": "2024",
                    "type": "doubles",
                    "surface": "clay",
                    "prize": "$25,000"
                },
                {
                    "name": "W35 Antalya (ITF)",
                    "season": "2024",
                    "type": "singles",
                    "surface": "clay",
                    "prize": "$25,000"
                },
                {
                    "name": "W35 Antalya 3 (ITF)",
                    "season": "2024",
                    "type": "singles",
                    "surface": "clay",
                    "prize": "$25,000"
                }
            ]
        }
    ]
}