{
    "success": 1,
    "result": [
        {
            "player_key": 118,
            "player_name": "H. Inoue",
            "player_country": "USA",
            "player_bday": "01.06.2003",
            "player_logo": null,
            "stats": [
                {
                    "season": "2022",
                    "type": "doubles",
                    "rank": "542",
                    "titles": "1",
                    "matches_won": "13",
                    "matches_lost": "8",
                    "hard_won": "10",
                    "hard_lost": "6",
                    "clay_won": "3",
                    "clay_lost": "2",
                    "grass_won": "",
                    "grass_lost": ""
                },
                {
                    "season": "2021",
                    "type": "doubles",
                    "rank": "1412",
                    "titles": "0",
                    "matches_won": "6",
                    "matches_lost": "9",
                    "hard_won": "5",
                    "hard_lost": "8",
                    "clay_won": "1",
                    "clay_lost": "1",
                    "grass_won": "",
                    "grass_lost": ""
                },
                {
                    "season": "2022",
                    "type": "singles",
                    "rank": "362",
                    "titles": "1",
                    "matches_won": "28",
                    "matches_lost": "23",
                    "hard_won": "22",
                    "hard_lost": "19",
                    "clay_won": "6",
                    "clay_lost": "4",
                    "grass_won": "",
                    "grass_lost": ""
                },
                {
                    "season": "2021",
                    "type": "singles",
                    "rank": "727",
                    "titles": "1",
                    "matches_won": "20",
                    "matches_lost": "14",
                    "hard_won": "17",
                    "hard_lost": "11",
                    "clay_won": "3",
                    "clay_lost": "3",
                    "grass_won": "",
                    "grass_lost": ""
                },
                {
                    "season": "2023",
                    "type": "singles",
                    "rank": "471",
                    "titles": "1",
                    "matches_won": "26",
                    "matches_lost": "23",
                    "hard_won": "21",
                    "hard_lost": "16",
                    "clay_won": "5",
                    "clay_lost": "7",
                    "grass_won": "",
                    "grass_lost": ""
                },
                {
                    "season": "2023",
                    "type": "doubles",
                    "rank": "876",
                    "titles": "0",
                    "matches_won": "3",
                    "matches_lost": "9",
                    "hard_won": "3",
                    "hard_lost": "8",
                    "clay_won": "0",
                    "clay_lost": "1",
                    "grass_won": "",
                    "grass_lost": ""
                },
                {
                    "season": "2024",
                    "type": "doubles",
                    "rank": "887",
                    "titles": "0",
                    "matches_won": "1",
                    "matches_lost": "4",
                    "hard_won": "1",
                    "hard_lost": "4",
                    "clay_won": "",
                    "clay_lost": "",
                    "grass_won": "",
                    "grass_lost": ""
                },
                {
                    "season": "2024",
                    "type": "singles",
                    "rank": "433",
                    "titles": "2",
                    "matches_won": "29",
                    "matches_lost": "13",
                    "hard_won": "29",
                    "hard_lost": "13",
                    "clay_won": "",
                    "clay_lost": "",
                    "grass_won": "",
                    "grass_lost": ""
                }
            ],
            "tournaments": [
                {
                    "name": "W15 Cancun (ITF)",
                    "season": "2022",
                    "type": "singles",
                    "surface": "hard",
                    "prize": "$15,000"
                },
                {
                    "name": "W15 Cancun 7 (ITF)",
                    "season": "2021",
                    "type": "singles",
                    "surface": "hard",
                    "prize": "$15,000"
                },
                {
                    "name": "W15 Monastir 37 (ITF)",
                    "season": "2023",
                    "type": "singles",
                    "surface": "hard",
                    "prize": "$15,000"
                },
                {
                    "name": "W15 Monastir 12 (ITF)",
                    "season": "2024",
                    "type": "singles",
                    "surface": "hard",
                    "prize": "$15,000"
                },
                {
                    "name": "W15 Monastir 14 (ITF)",
                    "season": "2024",
                    "type": "singles",
                    "surface": "hard",
                    "prize": "$15,000"
                }
            ]
        }
    ]
}