{
    "success": 1,
    "result": [
        {
            "player_key": 1895,
            "player_name": "A. Bublik",
            "player_country": "Kazakhstan",
            "player_bday": "17.06.1997",
            "player_logo": "https://api.api-tennis.com/logo-tennis/1895_a-bublik.jpg",
            "stats": [
                {
                    "season": "2022",
                    "type": "doubles",
                    "rank": "170",
                    "titles": "0",
                    "matches_won": "12",
                    "matches_lost": "17",
                    "hard_won": "7",
                    "hard_lost": "8",
                    "clay_won": "2",
                    "clay_lost": "6",
                    "grass_won": "1",
                    "grass_lost": "2"
                },
                {
                    "season": "2021",
                    "type": "doubles",
                    "rank": "48",
                    "titles": "0",
                    "matches_won": "11",
                    "matches_lost": "23",
                    "hard_won": "4",
                    "hard_lost": "15",
                    "clay_won": "6",
                    "clay_lost": "5",
                    "grass_won": "1",
                    "grass_lost": "3"
                },
                {
                    "season": "2020",
                    "type": "doubles",
                    "rank": "90",
                    "titles": "0",
                    "matches_won": "6",
                    "matches_lost": "9",
                    "hard_won": "6",
                    "hard_lost": "7",
                    "clay_won": "0",
                    "clay_lost": "2",
                    "grass_won": "",
                    "grass_lost": ""
                },
                {
                    "season": "2019",
                    "type": "doubles",
                    "rank": "320",
                    "titles": "0",
                    "matches_won": "4",
                    "matches_lost": "9",
                    "hard_won": "3",
                    "hard_lost": "7",
                    "clay_won": "0",
                    "clay_lost": "0",
                    "grass_won": "1",
                    "grass_lost": "2"
                },
                {
                    "season": "2018",
                    "type": "doubles",
                    "rank": "309",
                    "titles": "0",
                    "matches_won": "7",
                    "matches_lost": "12",
                    "hard_won": "7",
                    "hard_lost": "11",
                    "clay_won": "",
                    "clay_lost": "",
                    "grass_won": "0",
                    "grass_lost": "1"
                },
                {
                    "season": "2017",
                    "type": "doubles",
                    "rank": "",
                    "titles": "0",
                    "matches_won": "0",
                    "matches_lost": "7",
                    "hard_won": "0",
                    "hard_lost": "6",
                    "clay_won": "0",
                    "clay_lost": "1",
                    "grass_won": "",
                    "grass_lost": ""
                },
                {
                    "season": "2016",
                    "type": "doubles",
                    "rank": "861",
                    "titles": "0",
                    "matches_won": "2",
                    "matches_lost": "6",
                    "hard_won": "2",
                    "hard_lost": "4",
                    "clay_won": "0",
                    "clay_lost": "2",
                    "grass_won": "",
                    "grass_lost": ""
                },
                {
                    "season": "2015",
                    "type": "doubles",
                    "rank": "892",
                    "titles": "0",
                    "matches_won": "0",
                    "matches_lost": "1",
                    "hard_won": "0",
                    "hard_lost": "1",
                    "clay_won": "",
                    "clay_lost": "",
                    "grass_won": "",
                    "grass_lost": ""
                },
                {
                    "season": "",
                    "type": "mixed_doubles",
                    "rank": "",
                    "titles": "",
                    "matches_won": "",
                    "matches_lost": "",
                    "hard_won": "",
                    "hard_lost": "",
                    "clay_won": "",
                    "clay_lost": "",
                    "grass_won": "",
                    "grass_lost": ""
                },
                {
                    "season": "0",
                    "type": "mixed_doubles",
                    "rank": "0",
                    "titles": "0",
                    "matches_won": "0",
                    "matches_lost": "0",
                    "hard_won": "0",
                    "hard_lost": "0",
                    "clay_won": "0",
                    "clay_lost": "0",
                    "grass_won": "0",
                    "grass_lost": "0"
                },
                {
                    "season": "1",
                    "type": "mixed_doubles",
                    "rank": "1",
                    "titles": "1",
                    "matches_won": "1",
                    "matches_lost": "1",
                    "hard_won": "1",
                    "hard_lost": "1",
                    "clay_won": "1",
                    "clay_lost": "1",
                    "grass_won": "1",
                    "grass_lost": "1"
                },
                {
                    "season": "2",
                    "type": "mixed_doubles",
                    "rank": "2",
                    "titles": "2",
                    "matches_won": "2",
                    "matches_lost": "2",
                    "hard_won": "2",
                    "hard_lost": "2",
                    "clay_won": "2",
                    "clay_lost": "2",
                    "grass_won": "2",
                    "grass_lost": "2"
                },
                {
                    "season": "2022",
                    "type": "singles",
                    "rank": "37",
                    "titles": "1",
                    "matches_won": "33",
                    "matches_lost": "27",
                    "hard_won": "21",
                    "hard_lost": "14",
                    "clay_won": "2",
                    "clay_lost": "6",
                    "grass_won": "9",
                    "grass_lost": "5"
                },
                {
                    "season": "2021",
                    "type": "singles",
                    "rank": "36",
                    "titles": "0",
                    "matches_won": "37",
                    "matches_lost": "29",
                    "hard_won": "24",
                    "hard_lost": "18",
                    "clay_won": "4",
                    "clay_lost": "6",
                    "grass_won": "7",
                    "grass_lost": "4"
                },
                {
                    "season": "2020",
                    "type": "singles",
                    "rank": "50",
                    "titles": "0",
                    "matches_won": "13",
                    "matches_lost": "18",
                    "hard_won": "9",
                    "hard_lost": "13",
                    "clay_won": "4",
                    "clay_lost": "5",
                    "grass_won": "",
                    "grass_lost": ""
                },
                {
                    "season": "2019",
                    "type": "singles",
                    "rank": "56",
                    "titles": "3",
                    "matches_won": "44",
                    "matches_lost": "31",
                    "hard_won": "34",
                    "hard_lost": "22",
                    "clay_won": "2",
                    "clay_lost": "4",
                    "grass_won": "8",
                    "grass_lost": "5"
                },
                {
                    "season": "2018",
                    "type": "singles",
                    "rank": "162",
                    "titles": "1",
                    "matches_won": "29",
                    "matches_lost": "31",
                    "hard_won": "26",
                    "hard_lost": "22",
                    "clay_won": "1",
                    "clay_lost": "5",
                    "grass_won": "2",
                    "grass_lost": "4"
                },
                {
                    "season": "2017",
                    "type": "singles",
                    "rank": "117",
                    "titles": "2",
                    "matches_won": "44",
                    "matches_lost": "27",
                    "hard_won": "34",
                    "hard_lost": "17",
                    "clay_won": "6",
                    "clay_lost": "6",
                    "grass_won": "4",
                    "grass_lost": "4"
                },
                {
                    "season": "2016",
                    "type": "singles",
                    "rank": "205",
                    "titles": "0",
                    "matches_won": "15",
                    "matches_lost": "12",
                    "hard_won": "13",
                    "hard_lost": "11",
                    "clay_won": "2",
                    "clay_lost": "1",
                    "grass_won": "",
                    "grass_lost": ""
                },
                {
                    "season": "2015",
                    "type": "singles",
                    "rank": "964",
                    "titles": "0",
                    "matches_won": "2",
                    "matches_lost": "1",
                    "hard_won": "2",
                    "hard_lost": "1",
                    "clay_won": "0",
                    "clay_lost": "0",
                    "grass_won": "",
                    "grass_lost": ""
                },
                {
                    "season": "2014",
                    "type": "singles",
                    "rank": "893",
                    "titles": "0",
                    "matches_won": "0",
                    "matches_lost": "1",
                    "hard_won": "0",
                    "hard_lost": "1",
                    "clay_won": "",
                    "clay_lost": "",
                    "grass_won": "",
                    "grass_lost": ""
                },
                {
                    "season": "2022",
                    "type": "mixed_doubles",
                    "rank": "",
                    "titles": "0",
                    "matches_won": "0",
                    "matches_lost": "1",
                    "hard_won": "",
                    "hard_lost": "",
                    "clay_won": "0",
                    "clay_lost": "1",
                    "grass_won": "",
                    "grass_lost": ""
                },
                {
                    "season": "2021",
                    "type": "mixed_doubles",
                    "rank": "",
                    "titles": "0",
                    "matches_won": "0",
                    "matches_lost": "1",
                    "hard_won": "0",
                    "hard_lost": "1",
                    "clay_won": "",
                    "clay_lost": "",
                    "grass_won": "0",
                    "grass_lost": "0"
                },
                {
                    "season": "2023",
                    "type": "doubles",
                    "rank": "224",
                    "titles": "0",
                    "matches_won": "6",
                    "matches_lost": "16",
                    "hard_won": "6",
                    "hard_lost": "12",
                    "clay_won": "0",
                    "clay_lost": "1",
                    "grass_won": "0",
                    "grass_lost": "2"
                },
                {
                    "season": "2023",
                    "type": "singles",
                    "rank": "32",
                    "titles": "2",
                    "matches_won": "28",
                    "matches_lost": "30",
                    "hard_won": "12",
                    "hard_lost": "19",
                    "clay_won": "5",
                    "clay_lost": "7",
                    "grass_won": "9",
                    "grass_lost": "2"
                },
                {
                    "season": "2024",
                    "type": "doubles",
                    "rank": "148",
                    "titles": "0",
                    "matches_won": "5",
                    "matches_lost": "7",
                    "hard_won": "2",
                    "hard_lost": "4",
                    "clay_won": "3",
                    "clay_lost": "3",
                    "grass_won": "",
                    "grass_lost": ""
                },
                {
                    "season": "2024",
                    "type": "singles",
                    "rank": "17",
                    "titles": "1",
                    "matches_won": "19",
                    "matches_lost": "11",
                    "hard_won": "14",
                    "hard_lost": "7",
                    "clay_won": "5",
                    "clay_lost": "4",
                    "grass_won": "",
                    "grass_lost": ""
                }
            ],
            "tournaments": [
                {
                    "name": "Montpellier",
                    "season": "2022",
                    "type": "singles",
                    "surface": "hard (indoor)",
                    "prize": "\u20ac490,990"
                },
                {
                    "name": "Monterrey (Challenger)",
                    "season": "2019",
                    "type": "singles",
                    "surface": "hard",
                    "prize": "$162,480"
                },
                {
                    "name": "Pau (Challenger)",
                    "season": "2019",
                    "type": "singles",
                    "surface": "hard (indoor)",
                    "prize": "\u20ac69,280"
                },
                {
                    "name": "Budapest (Challenger)",
                    "season": "2019",
                    "type": "singles",
                    "surface": "hard (indoor)",
                    "prize": "\u20ac46,600"
                },
                {
                    "name": "Bratislava (Challenger)",
                    "season": "2018",
                    "type": "singles",
                    "surface": "hard",
                    "prize": "\u20ac106,000"
                },
                {
                    "name": "Aptos (Challenger)",
                    "season": "2017",
                    "type": "singles",
                    "surface": "hard",
                    "prize": "$100,000"
                },
                {
                    "name": "Morelos (Challenger)",
                    "season": "2017",
                    "type": "singles",
                    "surface": "hard",
                    "prize": "$50,000"
                },
                {
                    "name": "Halle",
                    "season": "2023",
                    "type": "singles",
                    "surface": "grass",
                    "prize": "\u20ac2,195,175"
                },
                {
                    "name": "Antwerp",
                    "season": "2023",
                    "type": "singles",
                    "surface": "hard (indoor)",
                    "prize": "\u20ac673,630"
                },
                {
                    "name": "Montpellier",
                    "season": "2024",
                    "type": "singles",
                    "surface": "hard (indoor)",
                    "prize": "\u20ac579,320"
                }
            ]
        }
    ]
}